get_sqrt_of_four_divided_by_seventy_four/README.md
get_sqrt_of_four_divided_by_seventy_four/__init__.py
get_sqrt_of_four_divided_by_seventy_four/get_sqrt_of_four_divided_by_seventy_four/__init__.py
get_sqrt_of_four_divided_by_seventy_four/get_sqrt_of_four_divided_by_seventy_four/__pycache__/__init__.cpython-311.pyc
get_sqrt_of_four_divided_by_seventy_four/pyproject.toml
get_sqrt_of_four_divided_by_seventy_four/tests/__init__.py
get_sqrt_of_four_divided_by_seventy_four-0.2.0.dist-info/METADATA
get_sqrt_of_four_divided_by_seventy_four-0.2.0.dist-info/WHEEL
get_sqrt_of_four_divided_by_seventy_four-0.2.0.dist-info/RECORD
