Metadata-Version: 2.3
Name: get-sqrt-of-four-divided-by-seventy-four
Version: 0.2.0
Summary: 
Author: python1st-code
Author-email: python1st-code@github.com
Requires-Python: >=3.12
Classifier: Programming Language :: Python :: 3
Classifier: Programming Language :: Python :: 3.12
Classifier: Programming Language :: Python :: 3.13
